{
  "date": "2026-06-29",
  "code": "207940",
  "name": "삼성바이오로직스",
  "slug": "samsung-biologics",
  "stance": "small_entry",
  "trigger": "미국 헬스케어(XLV) +3.03% 강세 → 바이오 위탁생산(CDMO) 수요처인 글로벌 제약사 투자심리 개선. 삼성바이오로직스의 CDMO 수익성 향상 기대감 부각.",
  "current_price": 1343000,
  "change_pct": 0.0,
  "year_low": 1228000,
  "year_high": 1987000,
  "score_short": 65,
  "score_mid": 71,
  "ai_pick_reason": "미국 헬스케어 섹터의 강세가 삼성바이오로직스의 주요 수익원인 CDMO 사업에 긍정적 신호를 보내고 있어요. 글로벌 제약사들의 투자심리 개선이 위탁생산 수요로 이어질 수 있다는 점이 주목할 만한데요. 다만 52주 저가에서 불과 15% 정도 회복한 상태이고 RSI도 중립 수준이므로, 추가 상승 여력을 검토해볼 만한 타이밍으로 보여요.",
  "counter_view": "헬스케어 섹터 랠리가 미 증시 전체의 약세 속 상대적 강세일 수 있다는 점은 지속성 판단이 필요하다는 뜻이에요. 또한 CDMO 수요 개선 기대감이 실제 실적 개선으로 확실히 이어지려면 시간이 걸릴 수 있으며, 단기 변동성도 상당할 수 있어요.",
  "us_summary": "미 증시 소폭 하락 속 헬스케어·바이오테크 강세 돋보임 — 반도체·기술주 동반 약세로 성장주 회피 심화.",
  "generated_at": "06:00"
}