{
  "week_start": "2026-05-25",
  "week_end": "2026-05-31",
  "generated_at": "2026-05-31T23:00:23",
  "events": [
    {
      "date": "2026-05-25",
      "weekday": "월",
      "time": "",
      "title": "미국 메모리얼 데이 휴장",
      "category": "정책",
      "impact": "mid",
      "view": "뉴욕 증시 휴장으로 외국인 수급 신호 공백, 국내 시장은 자체 수급·재료에 집중하는 흐름 가능."
    },
    {
      "date": "2026-05-27",
      "weekday": "수",
      "time": "21:30",
      "title": "미국 1분기 GDP 수정치 발표",
      "category": "지표",
      "impact": "high",
      "view": "성장률 하향 수정 시 경기 둔화 우려로 수출 비중 높은 반도체·자동차 섹터에 하방 압력 가능."
    },
    {
      "date": "2026-05-28",
      "weekday": "목",
      "time": "",
      "title": "엔비디아 1분기 실적 발표",
      "category": "실적",
      "impact": "high",
      "view": "AI 반도체 수요 가이던스에 따라 SK하이닉스·삼성전자 HBM 관련주 변동성 확대 가능성."
    },
    {
      "date": "2026-05-28",
      "weekday": "목",
      "time": "09:00",
      "title": "한국 5월 산업생산 지표 발표",
      "category": "지표",
      "impact": "mid",
      "view": "반도체·제조업 생산 증감률이 코스피 경기민감주 전반의 단기 방향성 가늠 지표로 주목."
    },
    {
      "date": "2026-05-29",
      "weekday": "금",
      "time": "",
      "title": "코스피200 옵션 월물 만기일",
      "category": "만기",
      "impact": "high",
      "view": "만기 청산 물량 집중으로 장 후반 지수 변동성 확대 및 프로그램 매매 급변 구간 주의."
    },
    {
      "date": "2026-05-29",
      "weekday": "금",
      "time": "21:30",
      "title": "미국 4월 PCE 물가 발표",
      "category": "지표",
      "impact": "high",
      "view": "연준 금리 경로 재조정 가능성이 달러·원 환율에 즉각 반영되며 외국인 수급 방향 결정 변수."
    },
    {
      "date": "2026-05-30",
      "weekday": "토",
      "time": "22:00",
      "title": "미국 5월 미시간 소비자심리 확정치",
      "category": "지표",
      "impact": "mid",
      "view": "소비심리 급락 확인 시 다음 주 월요일 개장 전 투자심리에 선반영되며 내수·소비재주 관찰 필요."
    }
  ]
}